accuralai_canonicalize/__init__.py
accuralai_canonicalize/canonicalizer.py
accuralai_canonicalize-0.2.1.dist-info/METADATA
accuralai_canonicalize-0.2.1.dist-info/WHEEL
accuralai_canonicalize-0.2.1.dist-info/entry_points.txt
accuralai_canonicalize-0.2.1.dist-info/licenses/LICENSE
accuralai_canonicalize-0.2.1.dist-info/RECORD
